rtdl_num_embeddings.py
rtdl_num_embeddings-0.0.12.dist-info/licenses/LICENSE
rtdl_num_embeddings-0.0.12.dist-info/WHEEL
rtdl_num_embeddings-0.0.12.dist-info/METADATA
rtdl_num_embeddings-0.0.12.dist-info/RECORD
