Metadata-Version: 2.4
Name: rtdl_num_embeddings
Version: 0.0.12
Summary: On Embeddings for Numerical Features in Tabular Deep Learning.
Keywords: artificial intelligence,deep learning,library,python,pytorch,research,torch,tabular,tabular data
Author: Yury Gorishniy
Requires-Python: >=3.9
Classifier: Intended Audience :: Developers
Classifier: Intended Audience :: Science/Research
Classifier: License :: OSI Approved :: Apache Software License
Classifier: Programming Language :: Python :: 3
Classifier: Topic :: Scientific/Engineering :: Artificial Intelligence
Classifier: Topic :: Software Development :: Libraries :: Python Modules
License-File: LICENSE
Requires-Dist: torch>=1.12,<3
Project-URL: Code, https://github.com/yandex-research/rtdl-num-embeddings/tree/main/package/README.md
Project-URL: Documentation, https://github.com/yandex-research/rtdl-num-embeddings/tree/main/package/README.md
